mumerge/__init__.py
mumerge/__main__.py
mumerge/_version.py
mumerge/mumerge.py
mumerge/bin/bedtools
mumerge/demo/a.bed
mumerge/demo/b.bed
mumerge/demo/mumerge_demo.input
mumerge/sim/__init__.py
mumerge/sim/mumerge_sim_unit.py
mumerge/test/__init__.py
mumerge/test/mumerge_unittest.py
mumerge-1.1.0.dist-info/AUTHORS.rst
mumerge-1.1.0.dist-info/LICENSE
mumerge-1.1.0.dist-info/METADATA
mumerge-1.1.0.dist-info/WHEEL
mumerge-1.1.0.dist-info/entry_points.txt
mumerge-1.1.0.dist-info/top_level.txt
mumerge-1.1.0.dist-info/RECORD
