Metadata-Version: 2.1
Name: mumerge
Version: 1.1.0
Summary: A tool for combining bed regions from multiple bed files in a probabilistically prinipled manner.
Home-page: https://github.com/Dowell-Lab/mumerge
Author: Jacob T. Stanley
Author-email: jacob.stanley@colorado.edu
License: GPL v3.0
Platform: UNKNOWN
Classifier: Development Status :: 4 - Beta
Classifier: Natural Language :: English
Classifier: Programming Language :: Python :: 3
Requires-Python: >=3.6
License-File: LICENSE
License-File: AUTHORS.rst
Requires-Dist: numpy
